state_machine_framework/__init__.py
state_machine_framework-1.0.0.dist-info/LICENSE
state_machine_framework-1.0.0.dist-info/METADATA
state_machine_framework-1.0.0.dist-info/WHEEL
state_machine_framework-1.0.0.dist-info/top_level.txt
state_machine_framework-1.0.0.dist-info/RECORD
