Metadata-Version: 2.1
Name: state-machine-framework
Version: 1.0.0
Summary: A flexible state machine framework for Python
Author: State Machine Framework Team
License: MIT
Project-URL: Homepage, https://github.com/AbhigyaShridhar/python-state-machines
Project-URL: Documentation, https://github.com/AbhigyaShridhar/python-state-machines#readme
Project-URL: Repository, https://github.com/AbhigyaShridhar/python-state-machines
Project-URL: Issues, https://github.com/AbhigyaShridhar/python-state-machines/issues
Classifier: Development Status :: 4 - Beta
Classifier: Intended Audience :: Developers
Classifier: License :: OSI Approved :: MIT License
Classifier: Programming Language :: Python :: 3
Classifier: Programming Language :: Python :: 3.8
Classifier: Programming Language :: Python :: 3.9
Classifier: Programming Language :: Python :: 3.10
Classifier: Programming Language :: Python :: 3.11
Classifier: Programming Language :: Python :: 3.12
Classifier: Topic :: Software Development :: Libraries :: Python Modules
Requires-Python: >=3.8
License-File: LICENSE
Requires-Dist: pydantic>=1.8.0
Provides-Extra: dev
Requires-Dist: pytest>=7.0.0; extra == "dev"
Requires-Dist: pytest-cov>=4.0.0; extra == "dev"
Requires-Dist: black>=23.0.0; extra == "dev"
Requires-Dist: flake8>=6.0.0; extra == "dev"
Requires-Dist: mypy>=1.0.0; extra == "dev"
